markdown_include/__init__.py
markdown_include/include.py
markdown_include-0.8.1.dist-info/LICENSE.txt
markdown_include-0.8.1.dist-info/METADATA
markdown_include-0.8.1.dist-info/WHEEL
markdown_include-0.8.1.dist-info/top_level.txt
markdown_include-0.8.1.dist-info/RECORD
