Metadata-Version: 2.1
Name: markdown-include
Version: 0.8.1
Summary: A Python-Markdown extension which provides an 'include' function
Author-email: Chris MacMackin <cmacmackin@gmail.com>
License: GNU General Public License v3 (GPLv3)
Project-URL: project, https://github.com/cmacmackin/markdown-include
Keywords: Markdown,typesetting,include,plugin,extension
Classifier: Programming Language :: Python
Classifier: Development Status :: 5 - Production/Stable
Classifier: Intended Audience :: Developers
Classifier: Topic :: Internet :: WWW/HTTP :: Site Management
Classifier: Topic :: Software Development :: Documentation
Classifier: Topic :: Software Development :: Libraries :: Python Modules
Classifier: Topic :: Text Processing :: Filters
Classifier: Topic :: Text Processing :: Markup :: HTML
Classifier: License :: OSI Approved :: GNU General Public License v3 (GPLv3)
Requires-Python: >=3.7
Provides-Extra: tests
License-File: LICENSE.txt
